Metadata-Version: 1.1
Name: icicle
Version: 1.2.0
Summary: Python FrozenDict
Home-page: https://github.com/pcattori/icicle
Author: Pedro Cattori
Author-email: pcattori@gmail.com
License: MIT
Keywords: frozendict immutable hash mapping
Platform: UNKNOWN
Classifier: Development Status :: 5 - Production/Stable
Classifier: Intended Audience :: Developers
Classifier: License :: OSI Approved :: MIT License
Classifier: Programming Language :: Python
Classifier: Programming Language :: Python :: 2.7
Classifier: Programming Language :: Python :: 3.5
